es_user/.DS_Store
es_user/__init__.py
es_user/contact/__init__.py
es_user/contact/model.py
es_user/contact/schema.py
es_user/contact/service.py
es_user/db/__init__.py
es_user/db/pg.py
es_user/db/session.py
es_user/user/__init__.py
es_user/user/model.py
es_user/user/schema.py
es_user/user/service.py
es_user/util/CONSTANTS.py
es_user/util/__init__.py
es_user/util/enums.py
es_user/util/service.py
es_user-0.1.0.dist-info/LICENSE
es_user-0.1.0.dist-info/METADATA
es_user-0.1.0.dist-info/WHEEL
es_user-0.1.0.dist-info/RECORD
